package/meta/__init__.py
package/meta/api_client.py
package/meta/api_response.py
package/meta/configuration.py
package/meta/exceptions.py
package/meta/py.typed
package/meta/rest.py
package/meta/api/__init__.py
package/meta/api/beckn_application_platform_bpp_api.py
package/meta/api/beckn_provider_platform_bpp_api.py
package/meta/models/__init__.py
package/meta/models/ack.py
package/meta/models/cancellation_reasons.py
package/meta/models/cancellation_reasons_context.py
package/meta/models/cancellation_reasons_message.py
package/meta/models/circle.py
package/meta/models/city.py
package/meta/models/context.py
package/meta/models/country.py
package/meta/models/descriptor.py
package/meta/models/descriptor_additional_desc.py
package/meta/models/error.py
package/meta/models/get_cancellation_reasons.py
package/meta/models/get_cancellation_reasons_context.py
package/meta/models/get_rating_categories.py
package/meta/models/get_rating_categories_context.py
package/meta/models/get_return_reasons.py
package/meta/models/get_return_reasons_context.py
package/meta/models/image.py
package/meta/models/inline_object.py
package/meta/models/inline_object_message.py
package/meta/models/inline_object_message_ack.py
package/meta/models/location.py
package/meta/models/media_file.py
package/meta/models/option.py
package/meta/models/rating.py
package/meta/models/rating_categories.py
package/meta/models/rating_categories_context.py
package/meta/models/rating_categories_message.py
package/meta/models/rating_category.py
package/meta/models/return_reasons.py
package/meta/models/return_reasons_context.py
package/meta/models/return_reasons_message.py
package/meta/models/scalar.py
package/meta/models/scalar_range.py
package/meta/models/state.py
package/meta/models/tag.py
package/meta/models/tag_group.py
package/registry/__init__.py
package/registry/api_client.py
package/registry/api_response.py
package/registry/configuration.py
package/registry/exceptions.py
package/registry/py.typed
beckn_python-1.0.0.dist-info/METADATA
beckn_python-1.0.0.dist-info/WHEEL
beckn_python-1.0.0.dist-info/top_level.txt
beckn_python-1.0.0.dist-info/RECORD
