Metadata-Version: 2.4
Name: beckn-python
Version: 1.0.0
Summary: Python SDK for Beckn
Requires-Python: >=3.12
Requires-Dist: pydantic[email]>=2.10.3
Requires-Dist: requests>=2.32.3
